{"2018-11-02": {"current_date": "2018-11-02", "previous_date": "2018-11-02", "commitCount": 1387, "issueCount": 51, "openIssueCount": 23, "closedIssueCount": 28, "pullRequestCount": 36, "openPullRequestCount": 0, "mergedPullRequestCount": 31, "closedPullRequestCount": 5, "forkCount": 5, "starCount": 7, "watcherCount": 26}, "2018-12-01": {"current_date": "2018-12-01", "previous_date": "2018-12-01", "commitCount": 410, "issueCount": 41, "openIssueCount": 17, "closedIssueCount": 24, "pullRequestCount": 31, "openPullRequestCount": 0, "mergedPullRequestCount": 26, "closedPullRequestCount": 5, "forkCount": 8, "starCount": 10, "watcherCount": 26}}